fab_react_toolkit/__init__.py
fab_react_toolkit/apis.py
fab_react_toolkit/filters.py
fab_react_toolkit/interface.py
fab_react_toolkit/views.py
fab_react_toolkit/api/__init__.py
fab_react_toolkit/api/convert.py
fab_react_toolkit/api/decorators.py
fab_react_toolkit/api/utils.py
fab_react_toolkit/generic/__init__.py
fab_react_toolkit/generic/filters.py
fab_react_toolkit/generic/interface.py
fab_react_toolkit/generic/schema.py
fab_react_toolkit/generic/session.py
fab_react_toolkit-0.6.5.dist-info/licenses/LICENSE
fab_react_toolkit-0.6.5.dist-info/METADATA
fab_react_toolkit-0.6.5.dist-info/WHEEL
fab_react_toolkit-0.6.5.dist-info/top_level.txt
fab_react_toolkit-0.6.5.dist-info/RECORD
