Metadata-Version: 2.4
Name: fab-react-toolkit
Version: 0.6.5
Summary: A small example package
Author-email: Matthias Leinweber <m.leinweber@datatactics.de>
Project-URL: Homepage, https://github.com/dttctcs/fab-react-toolkit
Project-URL: Issues, https://github.com/dttctcs/fab-react-toolkit/issues
Classifier: Programming Language :: Python :: 3
Classifier: License :: OSI Approved :: MIT License
Classifier: Operating System :: OS Independent
Requires-Python: >=3.8
License-File: LICENSE
Requires-Dist: Flask-AppBuilder
Requires-Dist: Flask-Talisman
Dynamic: license-file
